yawn/__init__.py
yawn/conftest.py
yawn/manage.py
yawn/models.py
yawn/urls.py
yawn/management/__init__.py
yawn/management/commands/__init__.py
yawn/management/commands/examples.py
yawn/management/commands/exec.py
yawn/management/commands/webserver.py
yawn/management/commands/worker.py
yawn/management/tests/__init__.py
yawn/management/tests/test_examples.py
yawn/management/tests/test_exec.py
yawn/management/tests/test_manage.py
yawn/management/tests/test_webserver.py
yawn/management/tests/test_worker.py
yawn/migrations/0001_initial.py
yawn/migrations/0002_tasks_without_workflows.py
yawn/migrations/0003_alter_execution_id_alter_queue_id_alter_run_id_and_more.py
yawn/migrations/__init__.py
yawn/settings/__init__.py
yawn/settings/base.py
yawn/settings/debug.py
yawn/settings/test.py
yawn/staticfiles/asset-manifest.json
yawn/staticfiles/favicon.ico
yawn/staticfiles/index.html
yawn/staticfiles/service-worker.js
yawn/staticfiles/static/css/main.9cc9dede.css
yawn/staticfiles/static/css/main.9cc9dede.css.map
yawn/staticfiles/static/js/main.db782b94.js
yawn/staticfiles/static/js/main.db782b94.js.map
yawn/staticfiles/static/media/glyphicons-halflings-regular.448c34a5.woff2
yawn/staticfiles/static/media/glyphicons-halflings-regular.89889688.svg
yawn/staticfiles/static/media/glyphicons-halflings-regular.e18bbf61.ttf
yawn/staticfiles/static/media/glyphicons-halflings-regular.f4769f9b.eot
yawn/staticfiles/static/media/glyphicons-halflings-regular.fa277232.woff
yawn/task/__init__.py
yawn/task/helpers.py
yawn/task/models.py
yawn/task/serializers.py
yawn/task/views.py
yawn/task/tests/__init__.py
yawn/task/tests/test_helpers.py
yawn/task/tests/test_models.py
yawn/task/tests/test_views.py
yawn/user/__init__.py
yawn/user/permissions.py
yawn/user/serializers.py
yawn/user/views.py
yawn/user/tests/__init__.py
yawn/user/tests/test_views.py
yawn/utilities/__init__.py
yawn/utilities/cron.py
yawn/utilities/database.py
yawn/utilities/middleware.py
yawn/utilities/pagination.py
yawns-0.3.1.dist-info/licenses/LICENSE.txt
yawns-0.3.1.dist-info/METADATA
yawns-0.3.1.dist-info/WHEEL
yawns-0.3.1.dist-info/entry_points.txt
yawns-0.3.1.dist-info/top_level.txt
yawns-0.3.1.dist-info/RECORD
