Metadata-Version: 2.4
Name: yawns
Version: 0.3.1
Summary: Yet Another Workflow Engine, a subprocess-based DAG execution system
Author-email: Alec Clowes <aclowes@gmail.com>
Maintainer-email: Alec Clowes <aclowes@gmail.com>
License-Expression: MIT
Project-URL: Homepage, https://github.com/aclowes/yawn
Keywords: task,execution,subprocess,dag,workflow
Classifier: Development Status :: 4 - Beta
Classifier: Intended Audience :: Developers
Classifier: Topic :: Software Development :: Libraries :: Application Frameworks
Classifier: Programming Language :: Python :: 3 :: Only
Requires-Python: >=3.6
License-File: LICENSE.txt
Requires-Dist: psycopg2-binary>=2.7
Requires-Dist: Django>=3.1
Requires-Dist: djangorestframework>=3.10
Requires-Dist: whitenoise>=3.0
Requires-Dist: gunicorn>=19
Requires-Dist: pyyaml>=5.1
Provides-Extra: test
Requires-Dist: flake8; extra == "test"
Requires-Dist: pytest>=3.4; extra == "test"
Requires-Dist: pytest-cov; extra == "test"
Requires-Dist: pytz; extra == "test"
Requires-Dist: build; extra == "test"
Requires-Dist: twine; extra == "test"
Dynamic: license-file
